doxysphinx/__init__.py
doxysphinx/__main__.py
doxysphinx/cli.py
doxysphinx/doxygen.py
doxysphinx/html_parser.py
doxysphinx/process.py
doxysphinx/resources/custom.scss
doxysphinx/resources/toc_template.html.j2
doxysphinx/resources.py
doxysphinx/sphinx.py
doxysphinx/toc.py
doxysphinx/utils/__init__.py
doxysphinx/utils/contexts.py
doxysphinx/utils/exceptions.py
doxysphinx/utils/files.py
doxysphinx/utils/iterators.py
doxysphinx/utils/pathlib_fix.py
doxysphinx/utils/rst.py
doxysphinx/writer.py
doxysphinx-3.3.14.dist-info/METADATA
doxysphinx-3.3.14.dist-info/WHEEL
doxysphinx-3.3.14.dist-info/entry_points.txt
doxysphinx-3.3.14.dist-info/licenses/LICENSE.md
doxysphinx-3.3.14.dist-info/licenses/NOTICE.md
doxysphinx-3.3.14.dist-info/RECORD
