Metadata-Version: 2.4
Name: doxysphinx
Version: 3.3.14
Summary: Integrates doxygen html documentation with sphinx.
License: MIT
License-File: LICENSE.md
License-File: NOTICE.md
Keywords: DaC,docs-as-code,doxygen,sphinx
Author: Nirmal Sasidharan
Author-email: nirmal.sasidharan@de.bosch.com
Maintainer: Nirmal Sasidharan
Maintainer-email: nirmal.sasidharan@de.bosch.com
Requires-Python: >=3.9,<3.13
Classifier: Framework :: Sphinx :: Extension
Classifier: License :: OSI Approved :: MIT License
Classifier: Programming Language :: Python :: 3
Classifier: Programming Language :: Python :: 3.9
Classifier: Programming Language :: Python :: 3.10
Classifier: Programming Language :: Python :: 3.11
Classifier: Programming Language :: Python :: 3.12
Classifier: Topic :: Documentation
Classifier: Topic :: Documentation :: Sphinx
Classifier: Topic :: Software Development :: Build Tools
Classifier: Topic :: Software Development :: Documentation
Classifier: Topic :: Software Development :: Pre-processors
Classifier: Topic :: Text Processing :: Markup :: HTML
Classifier: Topic :: Text Processing :: Markup :: reStructuredText
Requires-Dist: click (>=8.1.3,<9.0.0)
Requires-Dist: click-log (>=0.4.0,<0.5.0)
Requires-Dist: colorama (>=0.4.6,<0.5.0) ; sys_platform == "windows"
Requires-Dist: libsass (>=0.22.0,<0.23.0)
Requires-Dist: lxml (>=4.9.2,<=5.2.1)
Requires-Dist: mpire (>=2.6.0,<3.0.0)
Requires-Dist: pyjson5 (>=1.6.2,<2.0.0)
Requires-Dist: pyparsing (>=3.0.9,<4.0.0)
Project-URL: Documentation, https://boschglobal.github.io/doxysphinx/
Project-URL: Homepage, https://github.com/boschglobal/doxysphinx
Project-URL: Repository, https://github.com/boschglobal/doxysphinx
